aiterm/AITermCLI.py
aiterm/__init__.py
aiterm_cli-0.9.5.dist-info/licenses/LICENSE
aiterm_cli-0.9.5.dist-info/METADATA
aiterm_cli-0.9.5.dist-info/WHEEL
aiterm_cli-0.9.5.dist-info/entry_points.txt
aiterm_cli-0.9.5.dist-info/top_level.txt
aiterm_cli-0.9.5.dist-info/RECORD
