Metadata-Version: 2.4
Name: aiterm-cli
Version: 0.9.5
Summary: AI-powered terminal tool assistant
Author: Fernando Mellado
License: MIT License
Classifier: Programming Language :: Python :: 3
Classifier: Programming Language :: Python :: 3.8
Classifier: Programming Language :: Python :: 3.9
Classifier: Programming Language :: Python :: 3.10
Classifier: Programming Language :: Python :: 3.11
Classifier: License :: OSI Approved :: MIT License
Classifier: Operating System :: OS Independent
Requires-Python: >=3.8
License-File: LICENSE
Requires-Dist: openai>=1.0.0
Requires-Dist: wcwidth>=0.2.0
Dynamic: license-file
